pyfile/__init__.py
pyfile/manager.py
pyfile_lib-0.0.3.dist-info/licenses/LICENSE
pyfile_lib-0.0.3.dist-info/METADATA
pyfile_lib-0.0.3.dist-info/WHEEL
pyfile_lib-0.0.3.dist-info/top_level.txt
pyfile_lib-0.0.3.dist-info/RECORD
